pycozmo/__init__.py
pycozmo/activity.py
pycozmo/anim.py
pycozmo/anim_controller.py
pycozmo/anim_encoder.py
pycozmo/audio.py
pycozmo/behavior.py
pycozmo/brain.py
pycozmo/camera.py
pycozmo/client.py
pycozmo/conn.py
pycozmo/emotions.py
pycozmo/event.py
pycozmo/exception.py
pycozmo/filter.py
pycozmo/frame.py
pycozmo/image_encoder.py
pycozmo/json_loader.py
pycozmo/lights.py
pycozmo/logger.py
pycozmo/object.py
pycozmo/procedural_face.py
pycozmo/protocol_ast.py
pycozmo/protocol_base.py
pycozmo/protocol_declaration.py
pycozmo/protocol_encoder.py
pycozmo/protocol_generator.py
pycozmo/protocol_utils.py
pycozmo/robot.py
pycozmo/robot_debug.py
pycozmo/run.py
pycozmo/util.py
pycozmo/window.py
pycozmo/CozmoAnim/AnimClip.py
pycozmo/CozmoAnim/AnimClips.py
pycozmo/CozmoAnim/BackpackLights.py
pycozmo/CozmoAnim/BodyMotion.py
pycozmo/CozmoAnim/Event.py
pycozmo/CozmoAnim/FaceAnimation.py
pycozmo/CozmoAnim/HeadAngle.py
pycozmo/CozmoAnim/Keyframes.py
pycozmo/CozmoAnim/LiftHeight.py
pycozmo/CozmoAnim/ProceduralFace.py
pycozmo/CozmoAnim/RecordHeading.py
pycozmo/CozmoAnim/RobotAudio.py
pycozmo/CozmoAnim/TurnToRecordedHeading.py
pycozmo/CozmoAnim/__init__.py
pycozmo/audiokinetic/__init__.py
pycozmo/audiokinetic/exception.py
pycozmo/audiokinetic/soundbank.py
pycozmo/audiokinetic/soundbanksinfo.py
pycozmo/audiokinetic/wem.py
pycozmo/audiokinetic/tests/__init__.py
pycozmo/audiokinetic/tests/test_soundbank.py
pycozmo/audiokinetic/tests/test_soundbanksinfo.py
pycozmo/expressions/__init__.py
pycozmo/expressions/expressions.py
pycozmo/tests/__init__.py
pycozmo/tests/image_encoder_fixtures.py
pycozmo/tests/test_anim_encoder.py
pycozmo/tests/test_conn.py
pycozmo/tests/test_decay_graph.py
pycozmo/tests/test_frame.py
pycozmo/tests/test_image_decoder.py
pycozmo/tests/test_image_encoder.py
pycozmo/tests/test_robot_debug.py
pycozmo/tests/test_window.py
pycozmo-0.8.0.data/scripts/pycozmo_app.py
pycozmo-0.8.0.data/scripts/pycozmo_dump.py
pycozmo-0.8.0.data/scripts/pycozmo_replay.py
pycozmo-0.8.0.dist-info/LICENSE.md
pycozmo-0.8.0.dist-info/METADATA
pycozmo-0.8.0.dist-info/NOTICE
pycozmo-0.8.0.dist-info/WHEEL
pycozmo-0.8.0.dist-info/top_level.txt
pycozmo-0.8.0.dist-info/RECORD
