Metadata-Version: 2.1
Name: pycozmo
Version: 0.8.0
Summary: A pure-Python communication library, alternative SDK, and application for the Cozmo robot.
Home-page: https://github.com/zayfod/pycozmo/
Author: Kaloyan Tenchov
Author-email: zayfod@gmail.com
License: MIT
Keywords: ddl,anki,cozmo,robot,robotics
Platform: UNKNOWN
Classifier: Development Status :: 4 - Beta
Classifier: License :: OSI Approved :: MIT License
Classifier: Programming Language :: Python
Classifier: Programming Language :: Python :: 3.6
Classifier: Programming Language :: Python :: 3.7
Classifier: Programming Language :: Python :: 3.8
Classifier: Programming Language :: Python :: 3.9
Classifier: Topic :: Software Development :: Libraries
Classifier: Topic :: Software Development :: Libraries :: Python Modules
Classifier: Intended Audience :: Developers
Classifier: Intended Audience :: Education
Requires-Python: >=3.6.0
Requires-Dist: dpkt
Requires-Dist: numpy
Requires-Dist: Pillow (>=6.0.0)
Requires-Dist: flatbuffers
